FPGA/verilog/experiments/lab-exe2/mult4x4.sv
module mult4x4
(
    input logic [3:0] a,
    input logic [3:0] b,
    output logic [7:0] product
);
    always_comb begin
        product = a*b;
    end
endmodule

FPGA/verilog/experiments/lab-exe2/tb_mult4x4.sv
//============================================================
// Testbench for mult4x4
//============================================================
`timescale 1ns/1ps

module tb_mult4x4;
    // 時間単位指定 (SystemVerilog推奨構文)
    timeunit 1ps;
    timeprecision 1ps;

    // 定数
    parameter CYCLE = 20000ps;
    // 信号宣言
    logic [3:0] a, b;
    logic [7:0] product;

    // DUT（Device Under Test）インスタンス
    mult4x4 u1(
        .a(a),
        .b(b),
        .product(product)
    );

    // テストパターン
    initial begin
        a = 4'b0000;
        forever #(CYCLE) a<=a+1;
    end

    initial begin
        b = 4'b1111;
        forever #(CYCLE) b<=b-1;
    end

    initial begin
        $dumpfile("tb_mult4x4.vcd");
        $dumpvars(0, tb_mult4x4);     // 全信号を記録
        #(CYCLE * 20);                 // 20サイクル分シミュレーション
        $finish;
    end
endmodule

FPGA/verilog/experiments/lab-exe2/tb_mult4x4.vcd
$date
	Thu Oct 16 06:05:03 2025
$end
$version
	ModelSim Version 10.5b
$end
$timescale
	1ps
$end

$scope module tb_mult4x4 $end
$var parameter 0 ! CYCLE $end
$var reg 4 " a [3:0] $end
$var reg 4 # b [3:0] $end
$var reg 8 $ product [7:0] $end

$scope module u1 $end
$var wire 1 % a [3] $end
$var wire 1 & a [2] $end
$var wire 1 ' a [1] $end
$var wire 1 ( a [0] $end
$var wire 1 ) b [3] $end
$var wire 1 * b [2] $end
$var wire 1 + b [1] $end
$var wire 1 , b [0] $end
$var reg 8 - product [7:0] $end
$upscope $end
$upscope $end
$enddefinitions $end
#0
$dumpvars
b0 "
b1111 #
b0 $
b0 -
r20000 !
0(
0'
0&
0%
1,
1+
1*
1)
$end
#20000
b1 "
b1110 #
0,
1(
b1110 -
b1110 $
#40000
b10 "
b1101 #
1,
0+
0(
1'
b11010 -
b11010 $
#60000
b11 "
b1100 #
0,
1(
b100100 -
b100100 $
#80000
b100 "
b1011 #
1,
1+
0*
0(
0'
1&
b101100 -
b101100 $
#100000
b101 "
b1010 #
0,
1(
b110010 -
b110010 $
#120000
b110 "
b1001 #
1,
0+
0(
1'
b110110 -
b110110 $
#140000
b111 "
b1000 #
0,
1(
b111000 -
b111000 $
#160000
b1000 "
b111 #
1,
1+
1*
0)
0(
0'
0&
1%
#180000
b1001 "
b110 #
0,
1(
b110110 -
b110110 $
#200000
b1010 "
b101 #
1,
0+
0(
1'
b110010 -
b110010 $
#220000
b1011 "
b100 #
0,
1(
b101100 -
b101100 $
#240000
b1100 "
b11 #
1,
1+
0*
0(
0'
1&
b100100 -
b100100 $
#260000
b1101 "
b10 #
0,
1(
b11010 -
b11010 $
#280000
b1110 "
b1 #
1,
0+
0(
1'
b1110 -
b1110 $
#300000
b1111 "
b0 #
0,
1(
b0 -
b0 $
#320000
b0 "
b1111 #
1,
1+
1*
1)
0(
0'
0&
0%
#340000
b1 "
b1110 #
0,
1(
b1110 -
b1110 $
#360000
b10 "
b1101 #
1,
0+
0(
1'
b11010 -
b11010 $
#380000
b11 "
b1100 #
0,
1(
b100100 -
b100100 $
